_libinjection.cpython-35m-x86_64-linux-gnu.so
libinjection/libinjection.py
libinjection/__init__.py
threatstack_agent_python-0.1.1.dist-info/RECORD
threatstack_agent_python-0.1.1.dist-info/METADATA
threatstack_agent_python-0.1.1.dist-info/top_level.txt
threatstack_agent_python-0.1.1.dist-info/WHEEL
threatstack_agent_python-0.1.1.dist-info/entry_points.txt
test/__init__.py
test/unit/test_sitecustomize.py
test/unit/__init__.py
test/unit/test_execProgram.py
test/unit/test_models.py
test/unit/test_receiver.py
test/unit/test_config.py
test/unit/test_agent.py
test/unit/test_util.py
test/unit/test_errors.py
threatstack/processor.py
threatstack/__init__.py
threatstack/buildVersion.py
threatstack/errors.py
threatstack/config.py
threatstack/receiver.py
threatstack/agent.py
threatstack/assister/__init__.py
threatstack/assister/sitecustomize.py
threatstack/control/__init__.py
threatstack/control/execProgram.py
threatstack/control/__main__.py
threatstack/models/event.py
threatstack/models/__init__.py
threatstack/models/dependenciesevent.py
threatstack/models/environmentinfoevent.py
threatstack/models/attackevent.py
threatstack/util/logger.py
threatstack/util/__init__.py
threatstack/util/platform_info.py
threatstack/util/common.py
threatstack/util/wrapper.py
threatstack/util/injection.py
threatstack/instrumentation/pty_wrap.py
threatstack/instrumentation/flask_wrap.py
threatstack/instrumentation/__init__.py
threatstack/instrumentation/pymysql.py
threatstack/instrumentation/global_wrap.py
threatstack/instrumentation/subprocess_wrap.py
threatstack/instrumentation/psycopg.py
threatstack/instrumentation/mysqldb.py
threatstack/instrumentation/django.py
threatstack/instrumentation/helper.py
threatstack/instrumentation/os_wrap.py
threatstack/instrumentation/django_redis.py
