Metadata-Version: 2.1
Name: threatstack-agent-python
Version: 0.1.1
Summary: Application Security Monitoring by Threat Stack
Home-page: https://www.threatstack.com
Author: Threat Stack Inc.
Author-email: support@threatstack.com
License: PROPRIETARY
Platform: UNKNOWN
Classifier: Programming Language :: Python :: 2.7
Classifier: Programming Language :: Python :: 3
Classifier: License :: Other/Proprietary License
Classifier: Operating System :: OS Independent
Requires-Python: >=2.7, !=3.0.*, !=3.1.*, !=3.2.*, !=3.3.*, !=3.4.*
Requires-Dist: colorlog (==4.2.1)
Requires-Dist: requests (==2.23.0)
Requires-Dist: simplejson (==3.17.0)
Requires-Dist: six (==1.15.0)
Requires-Dist: wrapt (==1.12.1)
